CHANGELOG
MANIFEST.in
README
setup.py
.git/COMMIT_EDITMSG
.git/FETCH_HEAD
.git/HEAD
.git/ORIG_HEAD
.git/config
.git/description
.git/index
.git/packed-refs
.git/hooks/applypatch-msg.sample
.git/hooks/commit-msg.sample
.git/hooks/post-update.sample
.git/hooks/pre-applypatch.sample
.git/hooks/pre-commit.sample
.git/hooks/pre-rebase.sample
.git/hooks/prepare-commit-msg.sample
.git/hooks/update.sample
.git/info/exclude
.git/logs/HEAD
.git/logs/refs/heads/master
.git/logs/refs/remotes/origin/master
.git/objects/0a/f250d789a7664cd6582fa16376a3388874978c
.git/objects/13/b1a74c62624252467507be5efcb8112844c39d
.git/objects/15/5b5ab3fb776b593c4967cb3b114a4b66c737ed
.git/objects/1a/50fb5df5125d7f8e5577a1418ff955d495cf56
.git/objects/25/f505736d954b22ee20a2e0d4fd4154dc6912b7
.git/objects/30/28cecd57a119ff74646c2e5873df035cdd9e94
.git/objects/30/69b6303365074b62a83be64eeb382a496d6a7c
.git/objects/3d/3dbb49239968dee659e28516698ed4cbe277d6
.git/objects/4a/a05387cc2eafb69a7c026f064fcecd51525b1d
.git/objects/50/08ddfcf53c02e82d7eee2e57c38e5672ef89f6
.git/objects/51/f5cd8f6e9e425c1044a3cfb770f99922240bc7
.git/objects/60/b7f8715d907a9a3c26d0352ce8ac9508db85d7
.git/objects/63/50a2a56357fb724ec4d803d67b4a3c657fde67
.git/objects/70/3796fb554a084d5fc14ef9157432d6410b2111
.git/objects/88/2fe0d4567e98be6b06a39e49dd222f630f29fa
.git/objects/88/52ba04bc261663d60338d5657b095bd62defca
.git/objects/8b/30d691595d42e620ddad2f357b516ed0b619fc
.git/objects/90/a0245b84576a0e20886a81ac741371d5b1e634
.git/objects/94/2b781a5f722b947a21f6989f6ad1a0882b89b4
.git/objects/9c/db500c8053b26c71a88d9db2063a0496bd5ada
.git/objects/a6/b8e880ba0b6b9654f29ce2981cc1c6b2562d6f
.git/objects/ac/1200a5fc65a060b7a5bbf9e983991a993f63a7
.git/objects/c5/e57c4798cc096563abd65be3d6f18ca55f16c7
.git/objects/d0/184056a7aa84ecff6cbeba82301e34a31abbd3
.git/objects/d7/20e9e2b74716299398633a5991a88e8eb1b1c8
.git/objects/df/79dfb4e097b306de3828fd079ec82088f48bc3
.git/objects/e5/43241571a0bd02a7964f5b6b776a63fb70180b
django_multiuploader_file.egg-info/PKG-INFO
django_multiuploader_file.egg-info/SOURCES.txt
django_multiuploader_file.egg-info/dependency_links.txt
django_multiuploader_file.egg-info/requires.txt
django_multiuploader_file.egg-info/top_level.txt
