Metadata-Version: 1.0
Name: django-multiuploader-file
Version: 2.0.2
Summary: A fork of django-multiuploader that allow upload any file type.
Home-page: https://github.com/matheussl/django_multiuploader
Author: Matheus Lima
Author-email: matheus.se@gmail.com
License: Apache License 2.0.1
Keywords: django ios notification push
Platform: UNKNOWN
